src/icache.v
// ============================================================
// Direct-Mapped Instruction Cache — Clean Rewrite
// Author:   Aryaman Gupta
// ============================================================

module icache (
    input  wire        clk,
    input  wire        rst,

    // CPU interface
    input  wire [31:0] cpu_addr,
    output reg         cache_hit,
    output reg  [31:0] instr_out,
    output reg         stall,

    // Memory interface
    input  wire [31:0] mem_data_in,
    input  wire        mem_data_valid,
    output reg         mem_rd_en,

    // Performance counters
    output reg  [31:0] miss_count,
    output reg  [31:0] hit_count
);

    // Cache storage (unpacked arrays)
    reg        valid [0:15];
    reg [25:0] tag   [0:15];
    reg [31:0] data  [0:15];

    // States
    localparam IDLE  = 2'd0;
    localparam MISS  = 2'd1;
    localparam FILL  = 2'd2;
    localparam SERVE = 2'd3;

    reg [1:0]  state;
    reg [31:0] miss_addr;
    reg [31:0] miss_data;

    integer j;

    always @(posedge clk) begin
        if (rst) begin
            for (j = 0; j < 16; j = j + 1) begin
                valid[j] <= 1'b0;
                tag[j]   <= 26'b0;
                data[j]  <= 32'b0;
            end
            cache_hit  <= 0;
            instr_out  <= 0;
            stall      <= 0;
            mem_rd_en  <= 0;
            miss_count <= 0;
            hit_count  <= 0;
            state      <= IDLE;
            miss_addr  <= 0;
            miss_data  <= 0;
        end else begin

            case (state)

                IDLE: begin
                    // Do hit check INSIDE always block — avoids Icarus wire scheduling issues
                    if (valid[cpu_addr[5:2]] && (tag[cpu_addr[5:2]] == cpu_addr[31:6])) begin
                        // HIT
                        cache_hit <= 1'b1;
                        instr_out <= data[cpu_addr[5:2]];
                        stall     <= 1'b0;
                        mem_rd_en <= 1'b0;
                        hit_count <= hit_count + 1;
                        // stay in IDLE
                    end else begin
                        // MISS
                        cache_hit  <= 1'b0;
                        instr_out  <= 32'h0;
                        stall      <= 1'b1;
                        mem_rd_en  <= 1'b1;
                        miss_addr  <= cpu_addr;
                        miss_count <= miss_count + 1;
                        state      <= MISS;
                    end
                end

                MISS: begin
                    stall     <= 1'b1;
                    cache_hit <= 1'b0;
                    mem_rd_en <= 1'b0;

                    if (mem_data_valid) begin
                        // Fill cache immediately when data arrives
                        valid[miss_addr[5:2]] <= 1'b1;
                        tag  [miss_addr[5:2]] <= miss_addr[31:6];
                        data [miss_addr[5:2]] <= mem_data_in;
                        instr_out <= mem_data_in;   // serve instruction
                        cache_hit <= 1'b1;
                        stall     <= 1'b0;          // un-stall pipeline
                        state     <= IDLE;
                    end
                end

                SERVE: begin
                    // Serve directly from miss_data — don't rely on array read-back
                    instr_out <= miss_data;
                    cache_hit <= 1'b1;
                    stall     <= 1'b0;
                    mem_rd_en <= 1'b0;
                    state     <= IDLE;
                end

                default: state <= IDLE;
            endcase
        end
    end

endmodule

tb/icache_tb.v
// ============================================================
// Testbench for icache.v
// ============================================================
// What we test:
//  1. On first access to an address → MISS, stall goes high
//  2. After memory fills the cache → stall drops, instruction appears
//  3. Second access to same address → HIT (no stall!)
//  4. Access to different addresses → fill multiple cache lines
//  5. Re-access previously seen address → HIT
// ============================================================

`timescale 1ns / 1ps  // time unit / precision for simulation

module icache_tb;

    // ===== Signals to drive the DUT (Device Under Test) =====
    reg         clk;
    reg         rst;
    reg  [31:0] cpu_addr;
    reg  [31:0] mem_data_in;
    reg         mem_data_valid;
    
    // ===== Signals FROM the DUT =====
    wire        cache_hit;
    wire [31:0] instr_out;
    wire        stall;
    wire        mem_rd_en;
    wire [31:0] miss_count;
    wire [31:0] hit_count;
    
    // ===== Instantiate the cache (DUT) =====
    icache DUT (
        .clk           (clk),
        .rst           (rst),
        .cpu_addr      (cpu_addr),
        .cache_hit     (cache_hit),
        .instr_out     (instr_out),
        .stall         (stall),
        .mem_data_in   (mem_data_in),
        .mem_data_valid(mem_data_valid),
        .mem_rd_en     (mem_rd_en),
        .miss_count    (miss_count),
        .hit_count     (hit_count)
    );
    
    // ===== Clock generation: 10ns period = 100 MHz =====
    initial clk = 0;
    always #5 clk = ~clk; // toggle every 5ns → 10ns period
    
    // ===== VCD dump — this creates the waveform file for GTKWave =====
    initial begin
        $dumpfile("sim/icache_tb.vcd"); // output file
        $dumpvars(0, icache_tb);        // dump ALL signals in this module
    end
    
    // ===== Task: simulate memory responding to a read request =====
    // This mimics what the instr_mem module would do
    task mem_respond;
        input [31:0] data;
        begin
            @(posedge clk); #1; // wait 1 cycle
            @(posedge clk); #1; // wait 2 cycles (2-cycle memory latency)
            mem_data_in    = data;
            mem_data_valid = 1;
            @(posedge clk); #1;
            mem_data_valid = 0;
        end
    endtask
    
    // ===== Task: check a condition and print PASS or FAIL =====
    task check;
        input         condition;
        input [127:0] test_name; // string as bit vector (Verilog style)
        begin
            if (condition)
                $display("  [PASS] %s", test_name);
            else
                $display("  [FAIL] %s", test_name);
        end
    endtask
    
    // ===== Main test sequence =====
    initial begin
        $display("============================================");
        $display("  iCache Testbench — Aryaman Gupta");
        $display("============================================");
        
        // Initialize all inputs
        rst           = 1;
        cpu_addr      = 32'h0;
        mem_data_in   = 32'h0;
        mem_data_valid = 0;
        
        // Apply reset for 2 cycles
        @(posedge clk); @(posedge clk);
        rst = 0;
        @(posedge clk);
        
        // =====================
        // TEST 1: First access — should MISS
        // =====================
        $display("\n--- Test 1: Cold miss at address 0x00000000 ---");
        cpu_addr = 32'h0000_0000;
        @(posedge clk);
        #1; // small delay to let combinational logic settle
        check(!cache_hit, "Should be a MISS on first access");
        check(stall,      "Pipeline should be stalled");
        check(mem_rd_en,  "Memory read should be requested");
        
        // Simulate memory responding with instruction 0xDEADBEEF
        fork
            mem_respond(32'hDEAD_BEEF);
        join
        
        @(posedge clk); #1;
        check(!stall,                      "Stall should be released after fill");
        check(cache_hit,                   "Should be a HIT after fill");
        check(instr_out == 32'hDEAD_BEEF, "Correct instruction returned");
        
        // =====================
        // TEST 2: Second access to same address — should HIT
        // =====================
        $display("\n--- Test 2: Second access to 0x00000000 (should hit) ---");
        @(posedge clk); #1;
        check(cache_hit,                   "Should be a HIT (already in cache)");
        check(!stall,                      "No stall on cache hit");
        check(instr_out == 32'hDEAD_BEEF, "Same instruction returned");
        
        // =====================
        // TEST 3: Different address — another miss
        // =====================
        $display("\n--- Test 3: New address 0x00000010 ---");
        cpu_addr = 32'h0000_0010; // different cache line (index=4)
        @(posedge clk); #1;
        check(!cache_hit, "MISS on new address");
        check(stall,      "Stall on miss");
        
        fork
            mem_respond(32'hCAFE_BABE);
        join
        
        @(posedge clk); #1;
        check(instr_out == 32'hCAFE_BABE, "Correct instruction for new address");
        
        // =====================
        // TEST 4: Return to address 0 — should still be in cache
        // =====================
        $display("\n--- Test 4: Return to 0x00000000 (should still hit) ---");
        cpu_addr = 32'h0000_0000;
        @(posedge clk); #1;
        check(cache_hit,                   "HIT on return to cached address");
        check(instr_out == 32'hDEAD_BEEF, "Original instruction still in cache");
        
        // =====================
        // TEST 5: Check hit/miss counters
        // =====================
        $display("\n--- Test 5: Performance counter check ---");
        $display("  Miss count: %0d (expected ~2)", miss_count);
        $display("  Hit count:  %0d (expected ~3)", hit_count);
        
        $display("\n============================================");
        $display("  Testbench complete.");
        $display("============================================");
        
        #100;
        $finish; // end simulation
    end
    
    // Optional: print signal values every clock for debugging
    initial begin
        $monitor("t=%0t | addr=%h | hit=%b | stall=%b | instr=%h | misses=%0d | hits=%0d",
                 $time, cpu_addr, cache_hit, stall, instr_out, miss_count, hit_count);
    end

endmodule

sim/icache_tb.vcd
$date
	Sat Apr 11 22:58:43 2026
$end
$version
	Icarus Verilog
$end
$timescale
	1ps
$end
$scope module icache_tb $end
$var wire 1 ! stall $end
$var wire 32 " miss_count [31:0] $end
$var wire 1 # mem_rd_en $end
$var wire 32 $ instr_out [31:0] $end
$var wire 32 % hit_count [31:0] $end
$var wire 1 & cache_hit $end
$var reg 1 ' clk $end
$var reg 32 ( cpu_addr [31:0] $end
$var reg 32 ) mem_data_in [31:0] $end
$var reg 1 * mem_data_valid $end
$var reg 1 + rst $end
$scope module DUT $end
$var wire 1 ' clk $end
$var wire 32 , cpu_addr [31:0] $end
$var wire 32 - mem_data_in [31:0] $end
$var wire 1 * mem_data_valid $end
$var wire 1 + rst $end
$var parameter 2 . FILL $end
$var parameter 2 / IDLE $end
$var parameter 2 0 MISS $end
$var parameter 2 1 SERVE $end
$var reg 1 & cache_hit $end
$var reg 32 2 hit_count [31:0] $end
$var reg 32 3 instr_out [31:0] $end
$var reg 1 # mem_rd_en $end
$var reg 32 4 miss_addr [31:0] $end
$var reg 32 5 miss_count [31:0] $end
$var reg 32 6 miss_data [31:0] $end
$var reg 1 ! stall $end
$var reg 2 7 state [1:0] $end
$var integer 32 8 j [31:0] $end
$upscope $end
$scope task check $end
$var reg 1 9 condition $end
$var reg 128 : test_name [127:0] $end
$upscope $end
$scope task mem_respond $end
$var reg 32 ; data [31:0] $end
$upscope $end
$upscope $end
$enddefinitions $end
$comment Show the parameter values. $end
$dumpall
b11 1
b1 0
b0 /
b10 .
$end
#0
$dumpvars
bx ;
bx :
x9
bx 8
bx 7
bx 6
bx 5
bx 4
bx 3
bx 2
b0 -
b0 ,
1+
0*
b0 )
b0 (
0'
x&
bx %
bx $
x#
bx "
x!
$end
#5000
b0 6
b0 4
b0 7
b0 %
b0 2
b0 "
b0 5
0#
0!
b0 $
b0 3
0&
b10000 8
1'
#10000
0'
#15000
0+
b10000 8
1'
#20000
0'
#25000
b1 7
b1 "
b1 5
1#
1!
1'
#30000
0'
#35000
0#
1'
#36000
b11011110101011011011111011101111 ;
b1110101011011000110010000100000011000100110010100100000011100100110010101110001011101010110010101110011011101000110010101100100 :
09
#40000
0'
#45000
1'
#50000
0'
#55000
1'
#56000
1*
b11011110101011011011111011101111 )
b11011110101011011011111011101111 -
#60000
0'
#65000
b0 7
0!
1&
b11011110101011011011111011101111 $
b11011110101011011011111011101111 3
1'
#66000
0*
#70000
0'
#75000
b1 %
b1 2
1'
#76000
b1110010011101010110001101110100011010010110111101101110001000000111001001100101011101000111010101110010011011100110010101100100 :
19
#80000
0'
#85000
b10 %
b10 2
1'
#86000
b10000 (
b10000 ,
b1110010011101010110001101110100011010010110111101101110001000000111001001100101011101000111010101110010011011100110010101100100 :
#90000
0'
#95000
b1 7
b10 "
b10 5
b10000 4
1#
1!
b0 $
b0 3
0&
1'
#96000
b11001010111111101011101010111110 ;
b1010011011101000110000101101100011011000010000001101111011011100010000001101101011010010111001101110011 :
#100000
0'
#105000
0#
1'
#110000
0'
#115000
1'
#116000
1*
b11001010111111101011101010111110 )
b11001010111111101011101010111110 -
#120000
0'
#125000
b0 7
0!
1&
b11001010111111101011101010111110 $
b11001010111111101011101010111110 3
1'
#126000
0*
#130000
0'
#135000
b11 %
b11 2
1'
#136000
b0 (
b0 ,
b100000011001100110111101110010001000000110111001100101011101110010000001100001011001000110010001110010011001010111001101110011 :
#140000
0'
#145000
b100 %
b100 2
b11011110101011011011111011101111 $
b11011110101011011011111011101111 3
1'
#146000
b1101110001000000111001101110100011010010110110001101100001000000110100101101110001000000110001101100001011000110110100001100101 :
#150000
0'
#155000
b101 %
b101 2
1'
#160000
0'
#165000
b110 %
b110 2
1'
#170000
0'
#175000
b111 %
b111 2
1'
#180000
0'
#185000
b1000 %
b1000 2
1'
#190000
0'
#195000
b1001 %
b1001 2
1'
#200000
0'
#205000
b1010 %
b1010 2
1'
#210000
0'
#215000
b1011 %
b1011 2
1'
#220000
0'
#225000
b1100 %
b1100 2
1'
#230000
0'
#235000
b1101 %
b1101 2
1'
#240000
0'
#245000
b1110 %
b1110 2
1'
