src/perf_counters.v
// ============================================================
// On-Chip Performance Counters
// ============================================================
// Author:   Aryaman Gupta
//
// Fix: snap_valid now holds HIGH for 2 cycles after dump_en
// so the UART sender and testbench can reliably catch it.
// ============================================================

module perf_counters (
    input  wire        clk,
    input  wire        rst,

    // Event inputs
    input  wire        cache_hit_event,
    input  wire        cache_miss_event,
    input  wire        stall_event,
    input  wire        branch_mispredict,

    // Control
    input  wire        dump_en,

    // Live counter outputs
    output reg  [31:0] cycle_count,
    output reg  [31:0] hit_count,
    output reg  [31:0] miss_count,
    output reg  [31:0] stall_count,
    output reg  [31:0] mispredict_count,

    // Snapshot outputs (latched at dump_en)
    output reg  [31:0] snap_cycles,
    output reg  [31:0] snap_hits,
    output reg  [31:0] snap_misses,
    output reg  [31:0] snap_stalls,
    output reg  [31:0] snap_mispredicts,
    output reg         snap_valid
);

    // 2-cycle snap_valid pulse: set on dump_en, cleared one cycle later
    reg snap_valid_next;

    always @(posedge clk) begin
        if (rst) begin
            cycle_count      <= 32'b0;
            hit_count        <= 32'b0;
            miss_count       <= 32'b0;
            stall_count      <= 32'b0;
            mispredict_count <= 32'b0;
            snap_cycles      <= 32'b0;
            snap_hits        <= 32'b0;
            snap_misses      <= 32'b0;
            snap_stalls      <= 32'b0;
            snap_mispredicts <= 32'b0;
            snap_valid       <= 1'b0;
            snap_valid_next  <= 1'b0;
        end else begin

            // ── always counting ──────────────────────────────
            cycle_count <= cycle_count + 1;

            if (cache_hit_event)   hit_count        <= hit_count        + 1;
            if (cache_miss_event)  miss_count       <= miss_count       + 1;
            if (stall_event)       stall_count      <= stall_count      + 1;
            if (branch_mispredict) mispredict_count <= mispredict_count + 1;

            // ── snapshot logic ────────────────────────────────
            // snap_valid stays HIGH for 2 cycles:
            //   cycle N:   dump_en=1  → latch counters, snap_valid_next=1
            //   cycle N+1: snap_valid=1 (from snap_valid_next), clear next
            //   cycle N+2: snap_valid=0
            snap_valid      <= snap_valid_next;
            snap_valid_next <= 1'b0;          // default: clear

            if (dump_en) begin
                snap_cycles      <= cycle_count;
                snap_hits        <= hit_count;
                snap_misses      <= miss_count;
                snap_stalls      <= stall_count;
                snap_mispredicts <= mispredict_count;
                snap_valid_next  <= 1'b1;     // will make snap_valid HIGH next cycle
            end

        end
    end

endmodule

tb/perf_counters_tb.v
`timescale 1ns / 1ps

module perf_counters_tb;

    reg clk, rst;
    reg cache_hit_event, cache_miss_event;
    reg stall_event, branch_mispredict;
    reg dump_en;

    wire [31:0] cycle_count, hit_count, miss_count;
    wire [31:0] stall_count, mispredict_count;
    wire [31:0] snap_cycles, snap_hits, snap_misses;
    wire [31:0] snap_stalls, snap_mispredicts;
    wire        snap_valid;

    perf_counters DUT (
        .clk              (clk),
        .rst              (rst),
        .cache_hit_event  (cache_hit_event),
        .cache_miss_event (cache_miss_event),
        .stall_event      (stall_event),
        .branch_mispredict(branch_mispredict),
        .dump_en          (dump_en),
        .cycle_count      (cycle_count),
        .hit_count        (hit_count),
        .miss_count       (miss_count),
        .stall_count      (stall_count),
        .mispredict_count (mispredict_count),
        .snap_cycles      (snap_cycles),
        .snap_hits        (snap_hits),
        .snap_misses      (snap_misses),
        .snap_stalls      (snap_stalls),
        .snap_mispredicts (snap_mispredicts),
        .snap_valid       (snap_valid)
    );

    initial clk = 0;
    always #5 clk = ~clk;

    initial begin
        $dumpfile("sim/perf_counters_tb.vcd");
        $dumpvars(0, perf_counters_tb);
    end

    // prints actual vs expected so you can see exact values on failure
    task check_eq;
        input [31:0] actual;
        input [31:0] expected;
        input [255:0] name;
        begin
            if (actual == expected)
                $display("  [PASS] %s (= %0d)", name, actual);
            else
                $display("  [FAIL] %s (expected %0d, got %0d)", name, expected, actual);
        end
    endtask

    task check_true;
        input        cond;
        input [255:0] name;
        begin
            if (cond) $display("  [PASS] %s", name);
            else      $display("  [FAIL] %s", name);
        end
    endtask

    initial begin
        $display("================================================");
        $display("  perf_counters Testbench - Aryaman Gupta");
        $display("================================================");

        // initialise all inputs
        rst              = 1;
        cache_hit_event  = 0;
        cache_miss_event = 0;
        stall_event      = 0;
        branch_mispredict= 0;
        dump_en          = 0;

        // hold reset 4 cycles
        @(posedge clk); @(posedge clk);
        @(posedge clk); @(posedge clk);
        rst = 0;
        // wait at negedge to be safely between clock edges
        @(negedge clk); @(negedge clk);

        // ── TEST 1: cycle_count is nonzero and ticking ────────
        $display("\n--- Test 1: Cycle counter is running ---");
        @(negedge clk); #1;
        check_true(cycle_count > 0, "cycle_count > 0 after reset released");
        @(negedge clk); @(negedge clk); @(negedge clk); @(negedge clk); #1;
        check_true(cycle_count > 4, "cycle_count > 4 after more cycles");

        // ── TEST 2: one cache hit ─────────────────────────────
        $display("\n--- Test 2: Cache hit event ---");
        // sample at negedge (mid-cycle) — safe from NBAs
        @(negedge clk); #1;
        $display("  hit_count before = %0d", hit_count);

        // fire event: go to posedge, set HIGH, next posedge clears
        @(posedge clk); #2; cache_hit_event = 1;
        @(posedge clk); #2; cache_hit_event = 0;
        // wait 3 more cycles then sample at negedge
        @(posedge clk); @(posedge clk); @(posedge clk);
        @(negedge clk); #1;
        $display("  hit_count after  = %0d", hit_count);
        check_eq(hit_count, 1, "hit_count == 1");

        // ── TEST 3: one cache miss ────────────────────────────
        $display("\n--- Test 3: Cache miss event ---");
        @(posedge clk); #2; cache_miss_event = 1;
        @(posedge clk); #2; cache_miss_event = 0;
        @(posedge clk); @(posedge clk); @(posedge clk);
        @(negedge clk); #1;
        check_eq(miss_count, 1, "miss_count == 1");

        // ── TEST 4: stall for 3 cycles ────────────────────────
        $display("\n--- Test 4: Stall event (3 cycles) ---");
        @(posedge clk); #2; stall_event = 1;
        @(posedge clk); @(posedge clk); @(posedge clk);
        #2; stall_event = 0;
        @(posedge clk); @(posedge clk);
        @(negedge clk); #1;
        check_eq(stall_count, 3, "stall_count == 3");

        // ── TEST 5: branch mispredict ─────────────────────────
        $display("\n--- Test 5: Branch mispredict ---");
        @(posedge clk); #2; branch_mispredict = 1;
        @(posedge clk); #2; branch_mispredict = 0;
        @(posedge clk); @(posedge clk); @(posedge clk);
        @(negedge clk); #1;
        check_eq(mispredict_count, 1, "mispredict_count == 1");

        // ── TEST 6: snapshot ──────────────────────────────────
        $display("\n--- Test 6: Snapshot on dump_en ---");
        // fire dump_en for 1 cycle
        @(posedge clk); #2; dump_en = 1;
        @(posedge clk); #2; dump_en = 0;
        // wait 2 cycles for snap_valid_next to propagate
        @(posedge clk); @(posedge clk);
        @(negedge clk); #1;

        check_true(snap_valid == 1,          "snap_valid HIGH");
        check_eq(snap_hits,   hit_count,     "snap_hits == hit_count");
        check_eq(snap_misses, miss_count,    "snap_misses == miss_count");
        check_eq(snap_stalls, stall_count,   "snap_stalls == stall_count");
        check_eq(snap_mispredicts, mispredict_count, "snap_mispredicts == mispredict_count");

        // ── TEST 7: snap_valid clears ─────────────────────────
        $display("\n--- Test 7: snap_valid clears ---");
        @(posedge clk); @(posedge clk);
        @(negedge clk); #1;
        check_true(snap_valid == 0, "snap_valid LOW after pulse");

        // ── TEST 8: multiple hits and misses ──────────────────
        $display("\n--- Test 8: 3 more hits and 2 more misses ---");
        // 3 hits
        @(posedge clk); #2; cache_hit_event = 1;
        @(posedge clk); #2; cache_hit_event = 0;
        @(posedge clk); #2; cache_hit_event = 1;
        @(posedge clk); #2; cache_hit_event = 0;
        @(posedge clk); #2; cache_hit_event = 1;
        @(posedge clk); #2; cache_hit_event = 0;
        // 2 misses
        @(posedge clk); #2; cache_miss_event = 1;
        @(posedge clk); #2; cache_miss_event = 0;
        @(posedge clk); #2; cache_miss_event = 1;
        @(posedge clk); #2; cache_miss_event = 0;
        // settle
        @(posedge clk); @(posedge clk); @(posedge clk);
        @(negedge clk); #1;
        // started at hit=1, miss=1 → now should be hit=4, miss=3
        check_eq(hit_count,  4, "hit_count == 4 (1 original + 3 new)");
        check_eq(miss_count, 3, "miss_count == 3 (1 original + 2 new)");

        // snapshot and verify
        @(posedge clk); #2; dump_en = 1;
        @(posedge clk); #2; dump_en = 0;
        @(posedge clk); @(posedge clk);
        @(negedge clk); #1;
        check_eq(snap_hits,   4, "snap_hits == 4");
        check_eq(snap_misses, 3, "snap_misses == 3");

        $display("\n================================================");
        $display("  Testbench complete.");
        $display("================================================");
        $display("\n  Final counter values:");
        $display("  cycle_count      = %0d", cycle_count);
        $display("  hit_count        = %0d", hit_count);
        $display("  miss_count       = %0d", miss_count);
        $display("  stall_count      = %0d", stall_count);
        $display("  mispredict_count = %0d", mispredict_count);

        #50; $finish;
    end

endmodule

sim/perf_counters_tb.vcd
$date
	Sat Apr 11 23:27:57 2026
$end
$version
	Icarus Verilog
$end
$timescale
	1ps
$end
$scope module perf_counters_tb $end
$var wire 32 ! stall_count [31:0] $end
$var wire 1 " snap_valid $end
$var wire 32 # snap_stalls [31:0] $end
$var wire 32 $ snap_misses [31:0] $end
$var wire 32 % snap_mispredicts [31:0] $end
$var wire 32 & snap_hits [31:0] $end
$var wire 32 ' snap_cycles [31:0] $end
$var wire 32 ( miss_count [31:0] $end
$var wire 32 ) mispredict_count [31:0] $end
$var wire 32 * hit_count [31:0] $end
$var wire 32 + cycle_count [31:0] $end
$var reg 1 , branch_mispredict $end
$var reg 1 - cache_hit_event $end
$var reg 1 . cache_miss_event $end
$var reg 1 / clk $end
$var reg 1 0 dump_en $end
$var reg 1 1 rst $end
$var reg 1 2 stall_event $end
$scope module DUT $end
$var wire 1 , branch_mispredict $end
$var wire 1 - cache_hit_event $end
$var wire 1 . cache_miss_event $end
$var wire 1 / clk $end
$var wire 1 0 dump_en $end
$var wire 1 1 rst $end
$var wire 1 2 stall_event $end
$var reg 32 3 cycle_count [31:0] $end
$var reg 32 4 hit_count [31:0] $end
$var reg 32 5 mispredict_count [31:0] $end
$var reg 32 6 miss_count [31:0] $end
$var reg 32 7 snap_cycles [31:0] $end
$var reg 32 8 snap_hits [31:0] $end
$var reg 32 9 snap_mispredicts [31:0] $end
$var reg 32 : snap_misses [31:0] $end
$var reg 32 ; snap_stalls [31:0] $end
$var reg 1 " snap_valid $end
$var reg 1 < snap_valid_next $end
$var reg 32 = stall_count [31:0] $end
$upscope $end
$scope task check_eq $end
$var reg 32 > actual [31:0] $end
$var reg 32 ? expected [31:0] $end
$var reg 256 @ name [255:0] $end
$upscope $end
$scope task check_true $end
$var reg 1 A cond $end
$var reg 256 B name [255:0] $end
$upscope $end
$upscope $end
$enddefinitions $end
$comment Show the parameter values. $end
$dumpall
$end
#0
$dumpvars
bx B
xA
bx @
bx ?
bx >
bx =
x<
bx ;
bx :
bx 9
bx 8
bx 7
bx 6
bx 5
bx 4
bx 3
02
11
00
0/
0.
0-
0,
bx +
bx *
bx )
bx (
bx '
bx &
bx %
bx $
bx #
x"
bx !
$end
#5000
0<
0"
b0 %
b0 9
b0 #
b0 ;
b0 $
b0 :
b0 &
b0 8
b0 '
b0 7
b0 )
b0 5
b0 !
b0 =
b0 (
b0 6
b0 *
b0 4
b0 +
b0 3
1/
#10000
0/
#15000
1/
#20000
0/
#25000
1/
#30000
0/
#35000
01
1/
#40000
0/
#45000
b1 +
b1 3
1/
#50000
0/
#55000
b10 +
b10 3
1/
#60000
0/
#61000
b110010101011111011000110110111101110101011011100111010000100000001111100010000000110000001000000110000101100110011101000110010101110010001000000111001001100101011100110110010101110100001000000111001001100101011011000110010101100001011100110110010101100100 B
1A
#65000
b11 +
b11 3
1/
#70000
0/
#75000
b100 +
b100 3
1/
#80000
0/
#85000
b101 +
b101 3
1/
#90000
0/
#95000
b110 +
b110 3
1/
#100000
0/
#101000
b111100101100011011011000110010101011111011000110110111101110101011011100111010000100000001111100010000000110100001000000110000101100110011101000110010101110010001000000110110101101111011100100110010100100000011000110111100101100011011011000110010101110011 B
#105000
b111 +
b111 3
1/
#110000
0/
#115000
b1000 +
b1000 3
1/
#117000
1-
#120000
0/
#125000
b1 *
b1 4
b1001 +
b1001 3
1/
#127000
0-
#130000
0/
#135000
b1010 +
b1010 3
1/
#140000
0/
#145000
b1011 +
b1011 3
1/
#150000
0/
#155000
b1100 +
b1100 3
1/
#160000
0/
#161000
b110100001101001011101000101111101100011011011110111010101101110011101000010000000111101001111010010000000110001 @
b1 ?
b1 >
#165000
b1101 +
b1101 3
1/
#167000
1.
#170000
0/
#175000
b1 (
b1 6
b1110 +
b1110 3
1/
#177000
0.
#180000
0/
#185000
b1111 +
b1111 3
1/
#190000
0/
#195000
b10000 +
b10000 3
1/
#200000
0/
#205000
b10001 +
b10001 3
1/
#210000
0/
#211000
b11011010110100101110011011100110101111101100011011011110111010101101110011101000010000000111101001111010010000000110001 @
#215000
b10010 +
b10010 3
1/
#217000
12
#220000
0/
#225000
b1 !
b1 =
b10011 +
b10011 3
1/
#230000
0/
#235000
b10 !
b10 =
b10100 +
b10100 3
1/
#240000
0/
#245000
b11 !
b11 =
b10101 +
b10101 3
1/
#247000
02
#250000
0/
#255000
b10110 +
b10110 3
1/
#260000
0/
#265000
b10111 +
b10111 3
1/
#270000
0/
#271000
b1110011011101000110000101101100011011000101111101100011011011110111010101101110011101000010000000111101001111010010000000110011 @
b11 ?
b11 >
#275000
b11000 +
b11000 3
1/
#277000
1,
#280000
0/
#285000
b1 )
b1 5
b11001 +
b11001 3
1/
#287000
0,
#290000
0/
#295000
b11010 +
b11010 3
1/
#300000
0/
#305000
b11011 +
b11011 3
1/
#310000
0/
#315000
b11100 +
b11100 3
1/
#320000
0/
#321000
b11011010110100101110011011100000111001001100101011001000110100101100011011101000101111101100011011011110111010101101110011101000010000000111101001111010010000000110001 @
b1 ?
b1 >
#325000
b11101 +
b11101 3
1/
#327000
10
#330000
0/
#335000
1<
b1 %
b1 9
b11 #
b11 ;
b1 $
b1 :
b1 &
b1 8
b11101 '
b11101 7
b11110 +
b11110 3
1/
#337000
00
#340000
0/
#345000
0<
1"
b11111 +
b11111 3
1/
#350000
0/
#355000
0"
b100000 +
b100000 3
1/
#360000
0/
#361000
b1 ?
b1 >
b101111101101101011010010111001101110000011100100110010101100100011010010110001101110100011100110010000000111101001111010010000001101101011010010111001101110000011100100110010101100100011010010110001101110100010111110110001101101111011101010110111001110100 @
b11100110110111001100001011100000101111101110110011000010110110001101001011001000010000001001000010010010100011101001000 B
0A
#365000
b100001 +
b100001 3
1/
#370000
0/
#375000
b100010 +
b100010 3
1/
#380000
0/
#381000
b111001101101110011000010111000001011111011101100110000101101100011010010110010000100000010011000100111101010111001000000110000101100110011101000110010101110010001000000111000001110101011011000111001101100101 B
1A
#385000
b100011 +
b100011 3
1/
#387000
1-
#390000
0/
#395000
b10 *
b10 4
b100100 +
b100100 3
1/
#397000
0-
#400000
0/
#405000
b100101 +
b100101 3
1/
#407000
1-
#410000
0/
#415000
b11 *
b11 4
b100110 +
b100110 3
1/
#417000
0-
#420000
0/
#425000
b100111 +
b100111 3
1/
#427000
1-
#430000
0/
#435000
b100 *
b100 4
b101000 +
b101000 3
1/
#437000
0-
#440000
0/
#445000
b101001 +
b101001 3
1/
#447000
1.
#450000
0/
#455000
b10 (
b10 6
b101010 +
b101010 3
1/
#457000
0.
#460000
0/
#465000
b101011 +
b101011 3
1/
#467000
1.
#470000
0/
#475000
b11 (
b11 6
b101100 +
b101100 3
1/
#477000
0.
#480000
0/
#485000
b101101 +
b101101 3
1/
#490000
0/
#495000
b101110 +
b101110 3
1/
#500000
0/
#505000
b101111 +
b101111 3
1/
#510000
0/
#511000
b101111101100011011011110111010101101110011101000010000000111101001111010010000000110011001000000010100000110001001000000110111101110010011010010110011101101001011011100110000101101100001000000010101100100000001100100010000001101110011001010111011100101001 @
b11 ?
b11 >
#515000
b110000 +
b110000 3
1/
#517000
10
#520000
0/
#525000
1<
b11 $
b11 :
b100 &
b100 8
b110000 '
b110000 7
b110001 +
b110001 3
1/
#527000
00
#530000
0/
#535000
0<
1"
b110010 +
b110010 3
1/
#540000
0/
#545000
0"
b110011 +
b110011 3
1/
#550000
0/
#551000
b1110011011011100110000101110000010111110110110101101001011100110111001101100101011100110010000000111101001111010010000000110011 @
b11 ?
b11 >
#555000
b110100 +
b110100 3
1/
#560000
0/
#565000
b110101 +
b110101 3
1/
#570000
0/
#575000
b110110 +
b110110 3
1/
#580000
0/
#585000
b110111 +
b110111 3
1/
#590000
0/
#595000
b111000 +
b111000 3
1/
